CHANGES.txt
README.txt
setup.py
src/gocept/__init__.py
src/gocept.ctl.egg-info/PKG-INFO
src/gocept.ctl.egg-info/SOURCES.txt
src/gocept.ctl.egg-info/dependency_links.txt
src/gocept.ctl.egg-info/entry_points.txt
src/gocept.ctl.egg-info/namespace_packages.txt
src/gocept.ctl.egg-info/not-zip-safe
src/gocept.ctl.egg-info/requires.txt
src/gocept.ctl.egg-info/top_level.txt
src/gocept/ctl/__init__.py
