Metadata-Version: 1.0
Name: gocept.ctl
Version: 0.9
Summary: zc.buildout recipe to create a convenience-script for controlling services
Home-page: http://svn.gocept.com/repos/gocept/gocept.ctl
Author: Christian Theune
Author-email: ct@gocept.com
License: ZPL 2.1
Keywords: zope3 buildout
Platform: UNKNOWN
Classifier: Framework :: Buildout
